[
    {
        "title":"Choose cuisine",
        "description":"Lorem ipsum dolor sit dim amet, mea regione diamet principes at.",
        "image_path":"https://github.com/thanhphat219/Chuyen-de/blob/main/assets/pngwing.com%20(1).png?raw=true"
    },
    {
        "title":"Choose restaurant",
        "description":"Lorem ipsum dolor sit dim amet, mea regione diamet principes at.",
        "image_path":"https://github.com/thanhphat219/Chuyen-de/blob/main/assets/toppng.com-restaurant-png-512x512.png?raw=true"
    },
    {
        "title":"Select time,date",
        "description":"Lorem ipsum dolor sit dim amet, mea regione diamet principes at.",
        "image_path":"https://github.com/thanhphat219/Chuyen-de/blob/main/assets/toppng.com-date-and-time-897x983%20(1).png?raw=true"
    },
    {
        "title":"Select number of guest",
        "description":"Lorem ipsum dolor sit dim amet, mea regione diamet principes at.",
        "image_path":"https://github.com/thanhphat219/Chuyen-de/blob/main/assets/pngwing.com.png?raw=true"
    },
    {
        "title":"Prepayment",
        "description":"Lorem ipsum dolor sit dim amet, mea regione diamet principes at.",
        "image_path":"https://github.com/thanhphat219/Chuyen-de/blob/main/assets/pngegg.png?raw=true"
    },
    {
        "title":"Enjoy your time!",
        "description":"Lorem ipsum dolor sit dim amet, mea regione diamet principes at.",
        "image_path":"https://images.vexels.com/media/users/3/251369/isolated/preview/8d6a8603dc23f6ae9ba143993968a972-enjoy-quote-badge.png"
    }
]
